LICENSE
MANIFEST.in
README.md
pyproject.toml
examples/demo_app.py
fs_k8s_fastapi_helper/__init__.py
fs_k8s_fastapi_helper/service.py
fs_k8s_fastapi_helper.egg-info/PKG-INFO
fs_k8s_fastapi_helper.egg-info/SOURCES.txt
fs_k8s_fastapi_helper.egg-info/dependency_links.txt
fs_k8s_fastapi_helper.egg-info/requires.txt
fs_k8s_fastapi_helper.egg-info/top_level.txt
tests/__init__.py
tests/test_service.py