Metadata-Version: 2.4
Name: fs-k8s-fastapi-helper
Version: 0.1.0
Summary: A Kubernetes health check probe helper for FastAPI applications
Author-email: wuzh <wuzh@fxiaoke.com>
Maintainer-email: wuzh <wuzh@fxiaoke.com>
License-Expression: MIT
Project-URL: Homepage, https://git.firstshare.cn/devops/fs-k8s-fastapi-helper
Project-URL: Documentation, https://git.firstshare.cn/devops/fs-k8s-fastapi-helper
Project-URL: Repository, https://git.firstshare.cn/devops/fs-k8s-fastapi-helper
Project-URL: Bug Tracker, https://git.firstshare.cn/devops/fs-k8s-fastapi-helper/-/issues
Keywords: kubernetes,k8s,fastapi,health-check,probe,liveness,readiness,microservices
Classifier: Development Status :: 3 - Alpha
Classifier: Intended Audience :: Developers
Classifier: Topic :: Software Development :: Libraries :: Python Modules
Classifier: Topic :: System :: Systems Administration
Classifier: Topic :: Internet :: WWW/HTTP :: HTTP Servers
Classifier: Programming Language :: Python :: 3
Classifier: Programming Language :: Python :: 3.7
Classifier: Programming Language :: Python :: 3.8
Classifier: Programming Language :: Python :: 3.9
Classifier: Programming Language :: Python :: 3.10
Classifier: Programming Language :: Python :: 3.11
Classifier: Programming Language :: Python :: 3.12
Classifier: Operating System :: OS Independent
Classifier: Framework :: FastAPI
Requires-Python: >=3.7
License-File: LICENSE
Requires-Dist: fastapi[standard]>=0.100.0
Provides-Extra: dev
Requires-Dist: pytest>=6.0; extra == "dev"
Requires-Dist: pytest-asyncio>=0.18.0; extra == "dev"
Requires-Dist: black>=21.0; extra == "dev"
Requires-Dist: flake8>=3.8; extra == "dev"
Requires-Dist: mypy>=0.800; extra == "dev"
Requires-Dist: pre-commit>=2.15; extra == "dev"
Provides-Extra: test
Requires-Dist: pytest>=6.0; extra == "test"
Requires-Dist: pytest-asyncio>=0.18.0; extra == "test"
Requires-Dist: pytest-cov>=2.10; extra == "test"
Provides-Extra: docs
Requires-Dist: mkdocs>=1.2.0; extra == "docs"
Requires-Dist: mkdocs-material>=7.0; extra == "docs"
Dynamic: license-file
